electricity_data_fetching_tr/__init__.py
electricity_data_fetching_tr/core/__init__.py
electricity_data_fetching_tr/core/constants.py
electricity_data_fetching_tr/core/get_data.py
electricity_data_fetching_tr/core/update_data.py
electricity_data_fetching_tr/models/__init__.py
electricity_data_fetching_tr/models/balancing_market_prices.py
electricity_data_fetching_tr/models/base.py
electricity_data_fetching_tr/models/day_ahead_prices.py
electricity_data_fetching_tr/models/forecasted_demand.py
electricity_data_fetching_tr/models/forecasted_demand_supply.py
electricity_data_fetching_tr/models/forecasted_supply.py
electricity_data_fetching_tr-0.1.5.dist-info/LICENSE
electricity_data_fetching_tr-0.1.5.dist-info/METADATA
electricity_data_fetching_tr-0.1.5.dist-info/WHEEL
electricity_data_fetching_tr-0.1.5.dist-info/top_level.txt
electricity_data_fetching_tr-0.1.5.dist-info/RECORD
