Metadata-Version: 2.1
Name: electricity-data-fetching-tr
Version: 0.1.5
Summary: Uses the EPIAS API to fetch electricity data for Turkey. The package also cleans and structures the data to be used in forecasting models.
Home-page: https://github.com/rojenarda/electricity_data_fetching_tr
Author: Rojen Arda Şeşen
Author-email: sesen19@itu.edu.tr
License: GPL-3.0
Project-URL: Bug Tracker, https://github.com/yourusername/electricity_data_fetching_tr/issues
Project-URL: Source Code, https://github.com/yourusername/electricity_data_fetching_tr
Keywords: electricity data_fetching
Classifier: License :: OSI Approved :: GNU General Public License v3 (GPLv3)
License-File: LICENSE
Requires-Dist: numpy
Requires-Dist: requests
Requires-Dist: pandas
Requires-Dist: forex-python
Requires-Dist: workalendar
